django_cognito_saml/__init__.py
django_cognito_saml/apps.py
django_cognito_saml/backends.py
django_cognito_saml/conf.py
django_cognito_saml/mixins.py
django_cognito_saml/py.typed
django_cognito_saml/urls.py
django_cognito_saml/utils.py
django_cognito_saml/views.py
django_cognito_saml/tests/__init__.py
django_cognito_saml/tests/settings.py
django_cognito_saml/tests/tests.py
django_cognito_saml-0.1.8.dist-info/METADATA
django_cognito_saml-0.1.8.dist-info/WHEEL
django_cognito_saml-0.1.8.dist-info/RECORD
