Metadata-Version: 2.4
Name: django-cognito-saml
Version: 0.1.8
Author-email: william chu <william.chu@uptickhq.com>
Requires-Python: >=3.10
Requires-Dist: cryptography
Requires-Dist: django<5.2,>=3.2.0
Requires-Dist: pyjwt<3,>=2
Provides-Extra: dev
Requires-Dist: black>=23.1.0; extra == 'dev'
Requires-Dist: django-stubs>=1.15.0; extra == 'dev'
Requires-Dist: isort>=5.12.0; extra == 'dev'
Requires-Dist: mypy>=1.1.1; extra == 'dev'
Requires-Dist: pytest-django>=4.5.2; extra == 'dev'
Requires-Dist: pytest>=7.2.2; extra == 'dev'
Requires-Dist: ruff>=0.0.254; extra == 'dev'
Requires-Dist: tox>=4.4.6; extra == 'dev'
